ystockQuery/__init__.py
ystockQuery/ysHist.py
ystockQuery/ysHistData.py
ystockQuery/ystock.py
ystockQuery-0.1.0.dist-info/LICENSE
ystockQuery-0.1.0.dist-info/METADATA
ystockQuery-0.1.0.dist-info/WHEEL
ystockQuery-0.1.0.dist-info/top_level.txt
ystockQuery-0.1.0.dist-info/RECORD
