Metadata-Version: 2.1
Name: ystockQuery
Version: 0.1.0
Summary: A Yahoo Finance wrapper for stock quotes and historical data
Home-page: https://github.com/alancslhk/ystockQuery
Author: Alan Cheng
Author-email: alancslhkse@gmail.com
License: UNKNOWN
Platform: UNKNOWN
Classifier: Programming Language :: Python :: 3
Classifier: License :: OSI Approved :: MIT License
Classifier: Operating System :: OS Independent
Requires-Python: >=3.5
Requires-Dist: requests
